__init__.py
base.py
client.py
configuration.py
exceptions/__init__.py
exceptions/api_exception.py
handlers/__init__.py
handlers/handler.py
handlers/msgs/__init__.py
handlers/msgs/send_sms.py
helpers/__init__.py
helpers/api_helper.py
http/__init__.py
http/http_client.py
http/http_context.py
http/http_method_enum.py
http/http_request.py
http/http_response.py
http/requests_client.py
http/auth/__init__.py
http/auth/api_token.py
requests/__init__.py
requests/msgs/__init__.py
requests/msgs/send_sms.py
responses/__init__.py
responses/msgs/__init__.py
responses/msgs/send_sms.py
oursms-0.0.1.dist-info/LICENSE.txt
oursms-0.0.1.dist-info/METADATA
oursms-0.0.1.dist-info/WHEEL
oursms-0.0.1.dist-info/top_level.txt
oursms-0.0.1.dist-info/RECORD
