Metadata-Version: 2.1
Name: oursms
Version: 0.0.1
Summary: Oursms API client
Home-page: https://gitlab.com/abdroos/oursms
Author: Abdullah Alaidrous
Author-email: abd.alaidrous@gmail.com
Classifier: Programming Language :: Python :: 3
Classifier: License :: OSI Approved :: MIT License
Classifier: Operating System :: OS Independent
Requires-Python: >=3.6
License-File: LICENSE.txt
Requires-Dist: certifi ==2023.7.22
Requires-Dist: charset-normalizer ==3.3.0
Requires-Dist: idna ==3.4
Requires-Dist: jsonpickle ==3.0.2
Requires-Dist: python-dateutil ==2.8.2
Requires-Dist: requests ==2.31.0
Requires-Dist: six ==1.16.0
Requires-Dist: urllib3 ==2.0.7
